guolei_py3_hikvision/__init__.py
guolei_py3_hikvision/isc.py
guolei_py3_hikvision-0.0.3.dist-info/LICENSE
guolei_py3_hikvision-0.0.3.dist-info/METADATA
guolei_py3_hikvision-0.0.3.dist-info/WHEEL
guolei_py3_hikvision-0.0.3.dist-info/top_level.txt
guolei_py3_hikvision-0.0.3.dist-info/RECORD
