Metadata-Version: 2.1
Name: guolei-py3-hikvision
Version: 0.0.3
Summary: 海康威视 API
Home-page: https://github.com/guolei19850528/guolei_py3_hikvision
Author: guolei
Author-email: 174000902@qq.com
License: MIT
Requires-Python: >=3.0
License-File: LICENSE
Requires-Dist: addict
Requires-Dist: retrying
Requires-Dist: pydantic
Requires-Dist: guolei-py3-requests
